{"responses":{"200":{"content":{"application/json":{"schema":{"type":"object","properties":{"total_contracts":{"type":"integer"},"active_contracts":{"type":"integer"},"paused_contracts":{"type":"integer"},"total_events_indexed":{"type":"integer"},"last_event_timestamp":{"type":"string","format":"date-time","nullable":true},"events_per_minute":{"type":"integer"}},"required":["active_contracts","events_per_minute","last_event_timestamp","paused_contracts","total_contracts","total_events_indexed"],"title":"ContractStatusResponse"}}},"description":""}}}